setup.py
gaussian_and_binomial_distributions_Ga/Binomialdistribution.py
gaussian_and_binomial_distributions_Ga/Gaussiandistribution.py
gaussian_and_binomial_distributions_Ga/Generaldistribution.py
gaussian_and_binomial_distributions_Ga/__init__.py
gaussian_and_binomial_distributions_Ga.egg-info/PKG-INFO
gaussian_and_binomial_distributions_Ga.egg-info/SOURCES.txt
gaussian_and_binomial_distributions_Ga.egg-info/dependency_links.txt
gaussian_and_binomial_distributions_Ga.egg-info/not-zip-safe
gaussian_and_binomial_distributions_Ga.egg-info/top_level.txt