Metadata-Version: 1.0
Name: gaussian-and-binomial-distributions-Ga
Version: 1.1
Summary: Gaussian and Binomial distributions
Home-page: UNKNOWN
Author: UNKNOWN
Author-email: UNKNOWN
License: UNKNOWN
Platform: UNKNOWN
